CHANGES.rst
CONTRIBUTORS.rst
DEVELOP.rst
LICENSE.GPL
LICENSE.rst
MANIFEST.in
README.rst
setup.cfg
setup.py
docs/index.rst
src/collective/__init__.py
src/collective.symlink.egg-info/PKG-INFO
src/collective.symlink.egg-info/SOURCES.txt
src/collective.symlink.egg-info/dependency_links.txt
src/collective.symlink.egg-info/entry_points.txt
src/collective.symlink.egg-info/namespace_packages.txt
src/collective.symlink.egg-info/not-zip-safe
src/collective.symlink.egg-info/requires.txt
src/collective.symlink.egg-info/top_level.txt
src/collective/symlink/__init__.py
src/collective/symlink/configure.zcml
src/collective/symlink/indexes.py
src/collective/symlink/interfaces.py
src/collective/symlink/permissions.zcml
src/collective/symlink/setuphandlers.py
src/collective/symlink/testing.py
src/collective/symlink/upgrades.py
src/collective/symlink/upgrades.zcml
src/collective/symlink/utils.py
src/collective/symlink/browser/__init__.py
src/collective/symlink/browser/configure.zcml
src/collective/symlink/browser/editlinkviewlet.py
src/collective/symlink/browser/namechooser.py
src/collective/symlink/browser/symlinkname.py
src/collective/symlink/browser/overrides/.gitkeep
src/collective/symlink/browser/static/.gitkeep
src/collective/symlink/browser/templates/editlinkviewlet.pt
src/collective/symlink/content/__init__.py
src/collective/symlink/content/configure.zcml
src/collective/symlink/content/subscriber.py
src/collective/symlink/content/symlink.py
src/collective/symlink/locales/README.rst
src/collective/symlink/locales/__init__.py
src/collective/symlink/locales/collective.symlink.pot
src/collective/symlink/locales/update.py
src/collective/symlink/locales/update.sh
src/collective/symlink/locales/en/LC_MESSAGES/collective.symlink.po
src/collective/symlink/profiles/default/browserlayer.xml
src/collective/symlink/profiles/default/catalog.xml
src/collective/symlink/profiles/default/metadata.xml
src/collective/symlink/profiles/default/registry.xml
src/collective/symlink/profiles/default/rolemap.xml
src/collective/symlink/profiles/default/types.xml
src/collective/symlink/profiles/default/types/symlink.xml
src/collective/symlink/profiles/uninstall/browserlayer.xml
src/collective/symlink/tests/__init__.py
src/collective/symlink/tests/test_robot.py
src/collective/symlink/tests/test_setup.py
src/collective/symlink/tests/test_symlink.py
